{
  "data": [
    {
      "ID": "a7a1345e-1bc8-4793-9650-a0ee89b6d74b",
      "Title": "QQ 群",
      "Content": "",
      "Tags": "其他",
      "Status": 4,
      "Type": "post",
      "IsPined": 1,
      "IsRecommend": 2,
      "IsOriginal": 1,
      "CreatedAt": "2022-05-24T21:00:39+08:00",
      "UpdatedAt": "2022-05-24T21:02:47+08:00",
      "Meta": {
        "TitleJapanese": "",
        "TitleRomanji": "",
        "Genre": "电影",
        "Region": "其他",
        "Episodes": 1,
        "IsEnd": 1,
        "PublishDate": null,
        "UpdatedDate": null
      },
      "Creator": {
        "ID": 1,
        "Name": "root",
        "Nickname": "YUESE",
        "Avatar": "https://q1.qlogo.cn/g?b=qq\u0026nk=7619376472\u0026s=640",
        "Bio": "这个人很酷，什么都没有留下"
      }
    },
    {
      "ID": "9",
      "Cover": "https://p.upyun.com/demo/tmp/jjJWPHMZ.webp",
      "Title": "秒速5厘米",
      "Content": "",
      "Tags": "其他",
      "Status": 4,
      "Type": "video",
      "IsPined": 1,
      "IsRecommend": 2,
      "IsOriginal": 1,
      "CreatedAt": "2022-05-24T21:00:39+08:00",
      "UpdatedAt": "2022-05-24T21:02:47+08:00",
      "Meta": {
        "TitleJapanese": "",
        "TitleRomanji": "",
        "Genre": "电影",
        "Region": "其他",
        "Episodes": 1,
        "IsEnd": 1,
        "PublishDate": null,
        "UpdatedDate": null
      },
      "Creator": {
        "ID": 1,
        "Name": "root",
        "Nickname": "YUESE",
        "Avatar": "https://q1.qlogo.cn/g?b=qq\u0026nk=7619376472\u0026s=640",
        "Bio": "这个人很酷，什么都没有留下"
      }
    },
    {
      "ID": "131478f2-31cd-446a-9cb2-15158b8c3efe",
      "Cover": "https://pic.cyol.com/img/20220307/img_96d0b6d39b4fb401a5b9ad295ef957fdbd_c.jpg",
      "Title": "花束般的恋爱",
      "Content": "",
      "Tags": "其他",
      "Status": 4,
      "Type": "video",
      "IsPined": 1,
      "IsRecommend": 2,
      "IsOriginal": 1,
      "CreatedAt": "2022-05-24T21:00:39+08:00",
      "UpdatedAt": "2022-05-24T21:02:47+08:00",
      "Meta": {
        "TitleJapanese": "",
        "TitleRomanji": "",
        "Genre": "电影",
        "Region": "其他",
        "Episodes": 1,
        "IsEnd": 1,
        "PublishDate": null,
        "UpdatedDate": null
      },
      "Creator": {
        "ID": 1,
        "Name": "root",
        "Nickname": "YUESE",
        "Avatar": "https://q1.qlogo.cn/g?b=qq\u0026nk=7619376472\u0026s=640",
        "Bio": "这个人很酷，什么都没有留下"
      }
    }
  ],
  "err": null
}
